<?xml version="1.0" encoding="utf-8"?>
<odoo>

    <record id="add_expensify_category_to_expense_product" model="ir.ui.view">
        <field name="name">product.product.add_expensify_category</field>
        <field name="model">product.product</field>
        <field name="inherit_id"
               ref="hr_expense.product_product_expense_form_view"/>
        <field name="arch" type="xml">
            <xpath expr="//field[@name='type']" position="before">
                <field name="expensify_category_id"
                       attrs="{'invisible': [('can_be_expensed', '=', False)]}"/>
            </xpath>
        </field>
    </record>

</odoo>
